flpinfo/__init__.py
flpinfo/__main__.py
flpinfo-0.1.1.dist-info/COPYING
flpinfo-0.1.1.dist-info/METADATA
flpinfo-0.1.1.dist-info/WHEEL
flpinfo-0.1.1.dist-info/entry_points.txt
flpinfo-0.1.1.dist-info/top_level.txt
flpinfo-0.1.1.dist-info/RECORD
