Metadata-Version: 2.1
Name: flpinfo
Version: 0.1.1
Summary: Prints basic information about an FL Studio project file (.flp)
Home-page: https://github.com/demberto/FLPInfo
Author: demberto
Author-email: demberto@protonmail.com
License: UNKNOWN
Project-URL: Source, https://github.com/demberto/FLPInfo
Project-URL: Documentation, https://flpinfo.rtfd.io
Project-URL: Changelog, https://github.com/demberto/FLPInfo/blob/master/CHANGELOG.md
Project-URL: Bug Tracker, https://github.com/demberto/FLPInfo/issues
Project-URL: TODO, https://github.com/demberto/FLPInspect/blob/master/TODO.md
Platform: UNKNOWN
Classifier: Development Status :: 3 - Alpha
Classifier: License :: OSI Approved :: GNU General Public License v3 (GPLv3)
Classifier: Operating System :: OS Independent
Classifier: Programming Language :: Python :: 3
Classifier: Programming Language :: Python :: 3 :: Only
Classifier: Programming Language :: Python :: 3.6
Classifier: Programming Language :: Python :: 3.7
Classifier: Programming Language :: Python :: 3.8
Classifier: Programming Language :: Python :: 3.9
Classifier: Programming Language :: Python :: 3.10
Requires-Python: >=3.6
License-File: COPYING
Requires-Dist: pyflp (>=1.0.1)
